{"playlist": "test", "product": "sportify", "version": 0.1, "songs": [{"artist": "AC/DC", "id": 0, "mood-position": {}, "bpm-position": {"168": "17.171 - 30.0", "169": "0 - 12.934", "171": "13.41 - 16.695"}, "bpm-positions": {}, "name": "T.N.T.", "uri": "spotify:track:7LRMbd3LEoV5wZJvXT1Lwb"}, {"artist": "MGMT", "id": 1, "mood-position": {}, "bpm-position": {"163": "0 - 24.845", "164": "25.333 - 28.735"}, "bpm-positions": {}, "name": "Kids - Radio Mix", "uri": "spotify:track:7lmKwWlnhemDDqex55schS"}]}